vllm_playground/__init__.py
vllm_playground/app.py
vllm_playground/benchmarks.json
vllm_playground/cli.py
vllm_playground/container_manager.py
vllm_playground/index.html
vllm_playground/assets/Claude.png
vllm_playground/assets/guidellm-logo-light.png
vllm_playground/assets/guidellm-logo.svg
vllm_playground/assets/guidellm.png
vllm_playground/assets/llmcompressor.png
vllm_playground/assets/start-vllm.gif
vllm_playground/assets/stop-vllm.gif
vllm_playground/assets/vllm-logo.svg
vllm_playground/assets/vllm-omni-logo.svg
vllm_playground/assets/vllm-playground-chinese-support.png
vllm_playground/assets/vllm-playground-claude-code.gif
vllm_playground/assets/vllm-playground-mcp-client.png
vllm_playground/assets/vllm-playground-mcp-config.png
vllm_playground/assets/vllm-playground-newUI.png
vllm_playground/assets/vllm-playground-pull.png
vllm_playground/assets/vllm-playground-structured-outputs.png
vllm_playground/assets/vllm-playground.png
vllm_playground/assets/vllm-recipes-1.png
vllm_playground/assets/vllm-recipes-2.png
vllm_playground/assets/vllm.jpeg
vllm_playground/assets/vllm.png
vllm_playground/assets/vllm_only.png
vllm_playground/config/example_configs.json
vllm_playground/config/stable_audio.yaml
vllm_playground/config/vllm_cpu.env
vllm_playground/mcp_client/__init__.py
vllm_playground/mcp_client/config.py
vllm_playground/mcp_client/manager.py
vllm_playground/recipes/README.md
vllm_playground/recipes/recipes_catalog.json
vllm_playground/recipes/sync_recipes.py
vllm_playground/static/css/claudecode.css
vllm_playground/static/css/guidellm.css
vllm_playground/static/css/mcp.css
vllm_playground/static/css/omni.css
vllm_playground/static/css/style.css
vllm_playground/static/js/app.js
vllm_playground/static/js/i18n.js
vllm_playground/static/js/locales/en.js
vllm_playground/static/js/locales/zh-CN.js
vllm_playground/static/js/modules/claudecode.js
vllm_playground/static/js/modules/guidellm.js
vllm_playground/static/js/modules/mcp.js
vllm_playground-0.1.4.dist-info/METADATA
vllm_playground-0.1.4.dist-info/WHEEL
vllm_playground-0.1.4.dist-info/entry_points.txt
vllm_playground-0.1.4.dist-info/licenses/LICENSE
vllm_playground-0.1.4.dist-info/RECORD
