Metadata-Version: 2.4
Name: vllm-playground
Version: 0.1.4
Summary: A web interface for managing and interacting with vLLM servers
Project-URL: Homepage, https://github.com/micytao/vllm-playground
Project-URL: Documentation, https://github.com/micytao/vllm-playground#readme
Project-URL: Repository, https://github.com/micytao/vllm-playground
Project-URL: Issues, https://github.com/micytao/vllm-playground/issues
Author: micytao
License-Expression: Apache-2.0
License-File: LICENSE
Keywords: ai,inference,llm,machine-learning,playground,vllm,web-interface
Classifier: Development Status :: 4 - Beta
Classifier: Environment :: Web Environment
Classifier: Framework :: FastAPI
Classifier: Intended Audience :: Developers
Classifier: Intended Audience :: Science/Research
Classifier: License :: OSI Approved :: Apache Software License
Classifier: Operating System :: OS Independent
Classifier: Programming Language :: Python :: 3
Classifier: Programming Language :: Python :: 3.9
Classifier: Programming Language :: Python :: 3.10
Classifier: Programming Language :: Python :: 3.11
Classifier: Programming Language :: Python :: 3.12
Classifier: Topic :: Internet :: WWW/HTTP :: HTTP Servers
Classifier: Topic :: Scientific/Engineering :: Artificial Intelligence
Requires-Python: >=3.9
Requires-Dist: aiohttp>=3.9.0
Requires-Dist: fastapi>=0.104.0
Requires-Dist: jinja2>=3.1.0
Requires-Dist: numpy>=1.24.0
Requires-Dist: psutil>=5.9.0
Requires-Dist: pydantic>=2.4.0
Requires-Dist: python-multipart>=0.0.6
Requires-Dist: requests>=2.31.0
Requires-Dist: uvicorn>=0.24.0
Requires-Dist: websockets>=12.0
Provides-Extra: all
Requires-Dist: guidellm>=0.3.1; extra == 'all'
Requires-Dist: mcp>=1.0.0; extra == 'all'
Requires-Dist: pre-commit>=3.0.0; extra == 'all'
Requires-Dist: pytest-asyncio>=0.21.0; extra == 'all'
Requires-Dist: pytest>=7.0.0; extra == 'all'
Requires-Dist: ruff>=0.14.0; extra == 'all'
Provides-Extra: benchmark
Requires-Dist: guidellm>=0.3.1; extra == 'benchmark'
Provides-Extra: dev
Requires-Dist: pre-commit>=3.0.0; extra == 'dev'
Requires-Dist: pytest-asyncio>=0.21.0; extra == 'dev'
Requires-Dist: pytest>=7.0.0; extra == 'dev'
Requires-Dist: ruff>=0.14.0; extra == 'dev'
Provides-Extra: mcp
Requires-Dist: mcp>=1.0.0; extra == 'mcp'
